Metadata-Version: 2.1
Name: ectyper
Version: 1.0.0rc1
Summary: Escherichia coli fast serotyping using both raw reads and assemblies with automatic species identification
Home-page: https://github.com/phac-nml/ecoli_serotyping
Author: Chad Laing, Kyrylo Bessonov, Sam Sung, Camille La Rose, 
Author-email: chad.laing@canada.ca, kyrylo.bessonov@canada.ca, sam.sung@canada.ca, claro100@uottawa.ca
License: Apache 2
Platform: UNKNOWN
